sherlockbikepy
