Metadata-Version: 2.1
Name: sherlockbikepy
Version: 0.2.0
Summary: Python library to interact with the sherlock.bike API
Home-page: https://github.com/pschmitt/sherlockbikepy
Author: Philipp Schmitt
Author-email: philipp@schmitt.co
License: GPL3
Platform: UNKNOWN
